README.md
setup.cfg
setup.py
common/__init__.py
common/api/__init__.py
common/api/services/__init__.py
common/api/services/account/__init__.py
common/api/services/account/account_pb2.py
common/api/services/account/account_pb2_grpc.py
common/api/services/common/__init__.py
common/api/services/common/common_pb2.py
common/api/services/common/common_pb2_grpc.py
common/api/services/discussion/__init__.py
common/api/services/discussion/discussion_pb2.py
common/api/services/discussion/discussion_pb2_grpc.py
common/api/services/explore/__init__.py
common/api/services/explore/explore_pb2.py
common/api/services/explore/explore_pb2_grpc.py
common/api/services/hashtag/__init__.py
common/api/services/hashtag/hashtag_pb2.py
common/api/services/hashtag/hashtag_pb2_grpc.py
common/api/services/history/__init__.py
common/api/services/history/history_pb2.py
common/api/services/history/history_pb2_grpc.py
common/api/services/mention/__init__.py
common/api/services/mention/mention_pb2.py
common/api/services/mention/mention_pb2_grpc.py
common/api/services/post/__init__.py
common/api/services/post/post_pb2.py
common/api/services/post/post_pb2_grpc.py
common/api/services/product/__init__.py
common/api/services/product/product_pb2.py
common/api/services/product/product_pb2_grpc.py
common/api/services/shop/__init__.py
common/api/services/shop/shop_pb2.py
common/api/services/shop/shop_pb2_grpc.py
common/api/services/stats/__init__.py
common/api/services/stats/stats_pb2.py
common/api/services/stats/stats_pb2_grpc.py
common/api/services/story/__init__.py
common/api/services/story/story_pb2.py
common/api/services/story/story_pb2_grpc.py
mgo_serializer/__init__.py
mgo_serializer/exceptions.py
mgo_serializer/fields.py
mgo_serializer/helpers.py
mgo_serializer/meta.py
mgo_serializer/serializer.py
mgo_serializer/utils.py
mgo_serializer.egg-info/PKG-INFO
mgo_serializer.egg-info/SOURCES.txt
mgo_serializer.egg-info/dependency_links.txt
mgo_serializer.egg-info/top_level.txt