Metadata-Version: 2.1
Name: mgo-serializer
Version: 0.0.17
Summary: A MongoEngine Serializer to serialize objects from JSON/BSON to JSON and gRPC
Home-page: https://github.com/its0x4d/mgo_serializer
Author: MosyDev
Author-email: mostafa.uwsgi@gmail.com
License: GPLv3
Platform: UNKNOWN
Classifier: Programming Language :: Python :: 3
Classifier: License :: OSI Approved :: GNU General Public License v3 (GPLv3)
